[
  {
    "full_name": "GREsau/schemars",
    "stargazers_count": 660,
    "open_issues_count": 133,
    "forks_count": 193
  },
  {
    "full_name": "loco-rs/loco",
    "stargazers_count": 2767,
    "open_issues_count": 30,
    "forks_count": 99
  },
  {
    "full_name": "emanuelef/daily-stars-explorer",
    "stargazers_count": 33,
    "open_issues_count": 8,
    "forks_count": 0
  },
  {
    "full_name": "regclient/regclient",
    "stargazers_count": 994,
    "open_issues_count": 12,
    "forks_count": 81
  },
  {
    "full_name": "krustlet/oci-distribution",
    "stargazers_count": 70,
    "open_issues_count": 11,
    "forks_count": 43
  },
  {
    "full_name": "tamasfe/aide",
    "stargazers_count": 285,
    "open_issues_count": 10,
    "forks_count": 47
  },
  {
    "full_name": "johalun/sysctl-rs",
    "stargazers_count": 46,
    "open_issues_count": 6,
    "forks_count": 20
  },
  {
    "full_name": "getzola/zola",
    "stargazers_count": 12413,
    "open_issues_count": 253,
    "forks_count": 876
  },
  {
    "full_name": "atuinsh/atuin",
    "stargazers_count": 16326,
    "open_issues_count": 173,
    "forks_count": 464
  },
  {
    "full_name": "Riskified/dynamic-environment",
    "stargazers_count": 69,
    "open_issues_count": 1,
    "forks_count": 3
  },
  {
    "full_name": "jef/streetmerchant",
    "stargazers_count": 4946,
    "open_issues_count": 18,
    "forks_count": 1316
  },
  {
    "full_name": "redefinedev/redefine-action",
    "stargazers_count": 19,
    "open_issues_count": 0,
    "forks_count": 0
  },
  {
    "full_name": "Schniz/fnm",
    "stargazers_count": 14783,
    "open_issues_count": 184,
    "forks_count": 388
  },
  {
    "full_name": "erxes/erxes",
    "stargazers_count": 3365,
    "open_issues_count": 251,
    "forks_count": 1086
  },
  {
    "full_name": "TheLunarCompany/lunar",
    "stargazers_count": 90,
    "open_issues_count": 1,
    "forks_count": 3
  },
  {
    "full_name": "konih/kubernetes-network-debugging",
    "stargazers_count": 2,
    "open_issues_count": 0,
    "forks_count": 0
  },
  {
    "full_name": "nix-community/cache-nix-action",
    "stargazers_count": 21,
    "open_issues_count": 8,
    "forks_count": 1
  },
  {
    "full_name": "console-rs/indicatif",
    "stargazers_count": 3994,
    "open_issues_count": 70,
    "forks_count": 231
  },
  {
    "full_name": "3Hren/msgpack-rust",
    "stargazers_count": 1044,
    "open_issues_count": 62,
    "forks_count": 119
  },
  {
    "full_name": "yonahd/kor",
    "stargazers_count": 779,
    "open_issues_count": 11,
    "forks_count": 63
  },
  {
    "full_name": "jamesmunns/postcard",
    "stargazers_count": 675,
    "open_issues_count": 39,
    "forks_count": 65
  },
  {
    "full_name": "metalbear-co/mirrord-vscode",
    "stargazers_count": 6,
    "open_issues_count": 10,
    "forks_count": 8
  },
  {
    "full_name": "metalbear-co/mirrord-intellij",
    "stargazers_count": 7,
    "open_issues_count": 37,
    "forks_count": 8
  },
  {
    "full_name": "tamasfe/termspin",
    "stargazers_count": 2,
    "open_issues_count": 1,
    "forks_count": 1
  },
  {
    "full_name": "hyperstackjs/hyperstack",
    "stargazers_count": 380,
    "open_issues_count": 4,
    "forks_count": 13
  },
  {
    "full_name": "samwho/recolor",
    "stargazers_count": 13,
    "open_issues_count": 0,
    "forks_count": 0
  },
  {
    "full_name": "Codium-ai/pr-agent",
    "stargazers_count": 3588,
    "open_issues_count": 20,
    "forks_count": 269
  },
  {
    "full_name": "AdamRussak/k8f",
    "stargazers_count": 39,
    "open_issues_count": 1,
    "forks_count": 5
  },
  {
    "full_name": "AvivRubys/bluesky-hebrew-feed",
    "stargazers_count": 4,
    "open_issues_count": 5,
    "forks_count": 1
  },
  {
    "full_name": "NAlexPear/tracing-stackdriver",
    "stargazers_count": 25,
    "open_issues_count": 0,
    "forks_count": 25
  }
]