[
  {
    "full_name": "apple/containerization",
    "stargazers_count": 7509,
    "open_issues_count": 33,
    "forks_count": 165
  },
  {
    "full_name": "brizzai/auto-mcp",
    "stargazers_count": 156,
    "open_issues_count": 9,
    "forks_count": 15
  },
  {
    "full_name": "yogeek/kubernetes-local-development",
    "stargazers_count": 62,
    "open_issues_count": 0,
    "forks_count": 7
  },
  {
    "full_name": "dimkr/goji",
    "stargazers_count": 1,
    "open_issues_count": 0,
    "forks_count": 0
  },
  {
    "full_name": "kafka-rust/kafka-rust",
    "stargazers_count": 1366,
    "open_issues_count": 53,
    "forks_count": 142
  },
  {
    "full_name": "robusta-dev/holmesgpt",
    "stargazers_count": 1082,
    "open_issues_count": 94,
    "forks_count": 126
  },
  {
    "full_name": "odoo/odoo",
    "stargazers_count": 44357,
    "open_issues_count": 8483,
    "forks_count": 28693
  },
  {
    "full_name": "saphyr-rs/saphyr",
    "stargazers_count": 154,
    "open_issues_count": 15,
    "forks_count": 21
  },
  {
    "full_name": "bearcove/merde",
    "stargazers_count": 177,
    "open_issues_count": 4,
    "forks_count": 9
  },
  {
    "full_name": "dimkr/tootik",
    "stargazers_count": 165,
    "open_issues_count": 12,
    "forks_count": 8
  },
  {
    "full_name": "guybuk/bridge-ds",
    "stargazers_count": 22,
    "open_issues_count": 4,
    "forks_count": 0
  },
  {
    "full_name": "boasiHQ/interactive-inputs",
    "stargazers_count": 19,
    "open_issues_count": 12,
    "forks_count": 1
  },
  {
    "full_name": "chartdb/chartdb",
    "stargazers_count": 17422,
    "open_issues_count": 103,
    "forks_count": 927
  },
  {
    "full_name": "jj-vcs/jj",
    "stargazers_count": 17430,
    "open_issues_count": 710,
    "forks_count": 582
  },
  {
    "full_name": "eshelyaron/kubed",
    "stargazers_count": 67,
    "open_issues_count": 0,
    "forks_count": 1
  },
  {
    "full_name": "celery/kombu",
    "stargazers_count": 3030,
    "open_issues_count": 223,
    "forks_count": 957
  },
  {
    "full_name": "makeplane/plane",
    "stargazers_count": 37241,
    "open_issues_count": 497,
    "forks_count": 2466
  },
  {
    "full_name": "EmbarkStudios/cargo-deny",
    "stargazers_count": 1993,
    "open_issues_count": 75,
    "forks_count": 100
  },
  {
    "full_name": "actix/actix",
    "stargazers_count": 8925,
    "open_issues_count": 36,
    "forks_count": 669
  },
  {
    "full_name": "siketyan/hyper-proxy2",
    "stargazers_count": 14,
    "open_issues_count": 0,
    "forks_count": 5
  },
  {
    "full_name": "rust-cli/config-rs",
    "stargazers_count": 2947,
    "open_issues_count": 133,
    "forks_count": 237
  },
  {
    "full_name": "daytonaio/daytona",
    "stargazers_count": 20972,
    "open_issues_count": 97,
    "forks_count": 2333
  },
  {
    "full_name": "meh/rust-tun",
    "stargazers_count": 566,
    "open_issues_count": 9,
    "forks_count": 162
  },
  {
    "full_name": "clearml/clearml",
    "stargazers_count": 6097,
    "open_issues_count": 506,
    "forks_count": 688
  },
  {
    "full_name": "simonask/libyaml-safer",
    "stargazers_count": 71,
    "open_issues_count": 5,
    "forks_count": 3
  },
  {
    "full_name": "ente-io/ente",
    "stargazers_count": 20569,
    "open_issues_count": 379,
    "forks_count": 1172
  },
  {
    "full_name": "GREsau/schemars",
    "stargazers_count": 1115,
    "open_issues_count": 87,
    "forks_count": 261
  },
  {
    "full_name": "loco-rs/loco",
    "stargazers_count": 7888,
    "open_issues_count": 33,
    "forks_count": 344
  },
  {
    "full_name": "emanuelef/daily-stars-explorer",
    "stargazers_count": 232,
    "open_issues_count": 7,
    "forks_count": 6
  },
  {
    "full_name": "regclient/regclient",
    "stargazers_count": 1578,
    "open_issues_count": 15,
    "forks_count": 102
  }
]